{
    "电影名称": "нерва ина",
    "上映时间": "2022-10-09(釜山电影节)/2023-10-25(韩国)",
    "类型": "剧情",
    "简介": "春光烂漫迷茫的世美梦见 closest friend summer faint on green clover field. She worries about her injured love interest Junho who is missing his dog and staying at hospital. Worlds apart, she sneaks off to the hospital trying to convince him to join school trip while hoping to confess her true feelings.",
    "豆 ф百点评分": "8.3/10 from 103,645 users",
    "豆瓣链接": "<https://movie.douban.com/subject/36088979/>",
    "IMDb评分": "",
    "图片链接": "<https://images.weserv.nl/?url=https://img9.doubanio.com/view/photo/l_ratio_poster/public/p2899331823.jpg>",
    "集数": "1"
}