{
    "text": " {\n\"title\": \"Last Summer (L'été derniers)\",\n\"year\": \"2023\",\n\"country\": [\"France\", \"Norway\"],\n\"genre\": [\"Drama\", \"Thriller\"],\n\"language\": \"French\",\n\"runtime\": \"104 minutes\",\n\"director\": \"Catherine Breillat\",\n\"cast\": [\n{\"name\": \"Lea Druker\", \"role\": \"Anne\"},\n{\"name\": \"Samuel Kircher\", \"role\": \"Theo\"},\n{\"name\": \"Olivier Rabourdin\", \"role\": \"Pierre\"},\n{\"name\": \"Clotilde Courau\", \"role\": \"Mina\"},\n{\"name\": \"Serena Hu\", \"role\": \"Serena\"},\n{\"name\": \"Angela Chen\", \"role\": \"Angela\"},\n{\"name\": \"Romain Maricau\", \"role\": \"Lucas\"},\n{\"name\": \"Romane Violeau\", \"role\": \"First customer Anne\"},\n{\"name\": \"Marie Lucas\", \"role\": \"Mother first customer Anne\"},\n{\"name\": \"Nelia Da Costa\", \"role\": \"Amanda\"},\n{\"name\": \"Lila-Rose Gilberti\", \"role\": \"Sara Evrard\"},\n{\"name\": \"Jean-Christophe Pilloix\", \"role\": \"Mr. Evrard\"},\n{\"name\": \"Karim Achoui\", \"role\": \"Avocat Theo\"},\n{\"name\": \"Marie Lebey\", \"role\": \"Secretary of the lawyer of Theo\"},\n{\"name\": \"Simon Drappier\", \"role\": \"Father of Lucas\"},\n{\"name\": \"Meriem Nouri\", \"role\": \"Hairstylist\"},\n{\"name\": \"Valerie Schlumberger\", \"role\": \"Invited to cocktails\"},\n{\"name\": \"Benjamin Magnard\", \"role\": \"Invited to cocktails\"},\n{\"name\": \"Jerome Kircher\", \"role\": \"Invited to cocktails\"}\n],\n\"crew\": [\n{\"department\": \"Writing\", \"name\": \"Pascal Bonitzer\", \"job\": \"Screenplay by\"},\n{\"department\": \"Writing\", \"name\": \"Catherine Breillat\", \"job\": \"Screenplay by\"},\n{\"department\": \"Writing\", \"name\": \"Maren Louise Kaehne\", \"job\": \"Screenplay by\"},\n{\"department\": \"Writing\", \"name\": \"May El-Toukhy\", \"job\": \"Screenplay by\"},\n{\"department\": \"Production design\", \"name\": \"\"},\n{\"department\": \"Art direction\", \"name\": \"\"},\n{\"department\": \"Set decoration\", \"name\": \"\"},\n{\"department\": \"Costume design\", \"name\": \"\"},\n{\"department\": \"Makeup department\", \"name\": \"\"},\n{\"department\": \"Sound department\", \"name\": \"\"},\n{\"deposition\": \"Director of photography\", \"name\": \"Jeanne Lapoirie\"},\n{\"department\": \"Editing\", \"name\": \"Francois Quiqueere\"}\n],\n\"plot\": \"Anne is a lawyer and lives happily with her husband Pierre and their two adopted daughters. But when Xavier moves in with them, things take an unexpected turn. Anne finds herself drawn to him despite his rude behavior, leading to dangerous consequences for both her career and family.\",\n\"awards\": [\n{\n\"event\": \"76th Cannes Film Festival\",\n\"category\": \"Golden Palm Award (nominated)\",\n\"person\": \"Catherine Breillat\"\n}\n],\n\"links\": {\n\"douban\": \"https://movie.douban.com/subject/35418779/\"\n}\n}"
}