{
    "电影名称": "蓝色巨人",
    "上映时间": "2023-02-17",
    "类型": "剧情/动画/音乐",
    "简介": "住在仙台的高中生・宫本大（山田裕贵 配音）深受爵士乐吸引，每天都独自在河边吹奏次中音萨克斯风。毕业后他来到东京，住进了高中同学・玉田俊二（冈山天音 配音）的公寓。某日，大在展演空间遇见同龄钢琴家・泽边雪祈（间宫祥太朗 配音），并邀请他共组乐团，受大影响而开始打鼓的玉田也加入组成3 人乐团“JASS”。连乐谱都看不懂，只是一心吹奏萨克斯风的大、从小就将一切献给爵士乐的雪祈、以及初学者玉田，以在日本最好的爵士乐具乐部表演并改变日本爵士乐风格为目标，尽全力投入在音乐活动之中。",
    "豆瓣评分": "8.3",
    "豆瓣链接": "https://movie.douban.com/subject/35634583/",
    "IMDb评分": "",
    "图片链接": "https://images.weserv.nl/?url=https://img9.doubanio.com/view/photo/l_ratio_poster/public/p2885199594.jpg",
    "制片国家": "日本"
}